README.md
arpsnitch.py
setup.py
arpsnitch.egg-info/PKG-INFO
arpsnitch.egg-info/SOURCES.txt
arpsnitch.egg-info/dependency_links.txt
arpsnitch.egg-info/not-zip-safe
arpsnitch.egg-info/requires.txt
arpsnitch.egg-info/top_level.txt