Metadata-Version: 1.0
Name: arpsnitch
Version: 0.1
Summary: a tool for checking hosts on the network via arp
Home-page: http://github.com/redimp/arpsnitch
Author: Ralph Thesen
Author-email: mail@redimp.de
License: MIT
Platform: UNKNOWN
